bl_predictor/__init__.py
bl_predictor/__main__.py
bl_predictor/bl-predictor_logo.png
bl_predictor/crawled_data.csv
bl_predictor/crawler.py
bl_predictor/gui.py
bl_predictor/gui_slider_widget.py
bl_predictor/models.py
bl_predictor/prediction_evaluation.py
bl_predictor-1.2.dist-info/LICENSE.txt
bl_predictor-1.2.dist-info/METADATA
bl_predictor-1.2.dist-info/WHEEL
bl_predictor-1.2.dist-info/entry_points.txt
bl_predictor-1.2.dist-info/top_level.txt
bl_predictor-1.2.dist-info/RECORD
