Metadata-Version: 2.1
Name: bl-predictor
Version: 1.2
Summary: A simple application for predicting game results for the German Bundesliga
Home-page: https://github.com/lgehring/bl-predictor
Author: Lukas Gehring, Anabel Stammer, Alex Brylka and Fabricio Aguilera-Galviz
Author-email: l.gehring@student.uni-tuebingen.de
License: UNKNOWN
Platform: UNKNOWN
Classifier: Programming Language :: Python :: 3.8
Classifier: License :: OSI Approved :: MIT License
Classifier: Operating System :: OS Independent
Classifier: Development Status :: 5 - Production/Stable
Classifier: Intended Audience :: End Users/Desktop
Classifier: Natural Language :: English
Requires-Python: >=3.8
Requires-Dist: pandas (~=1.1.3)
Requires-Dist: setuptools (~=50.3.0)
Requires-Dist: statsmodels (~=0.12.1)
Requires-Dist: numpy (~=1.19.3)
Requires-Dist: scipy (~=1.5.2)
Requires-Dist: matplotlib (~=3.3.4)
Requires-Dist: pytest (~=6.1.2)
Requires-Dist: requests (~=2.24.0)
Requires-Dist: pillow (~=8.1.0)
Requires-Dist: lxml (~=4.6.1)
Requires-Dist: tabulate (~=0.8.7)
Requires-Dist: scikit-learn (~=0.24.1)
Requires-Dist: ttkthemes (~=3.2.2)
